{
    "name": "The Crypt",
    "mob_definitions": [ "mobs.json" ],
    "waves": [
        {
            "duration": 100,
            "spawn_rate": 1.0,
            "mobs": [
                { "weight": 2, "name": "skeleton", "min": 5, "max": 10 },
                { "weight": 2, "name": "zombie", "min": 5, "max": 10 },
                { "weight": 1, "name": "bat", "min": 2, "max": 5 }
            ]
        },
        {
            "duration": 100,
            "spawn_rate": 2.0,
            "mobs": [
                { "weight": 1, "name": "skeleton", "min": 5, "max": 10 },
                { "weight": 1, "name": "zombie", "min": 5, "max": 10 },
                { "weight": 1, "name": "bat", "min": 2, "max": 5 }
            ]
        }
    ]
}